[
  {
    "segment": "贸易",
    "periods": {
      "2025半年报": 310.58,
      "2024年报": 551.42,
      "2024半年报": 366.29,
      "2023年报": 793.08,
      "2023半年报": 355.64,
      "2022年报": 604.33,
      "2022半年报": 215.27,
      "2021年报": 180.84,
      "2021半年报": 63.699608,
      "2020年报": 121.31,
      "2019年报": 308.668534,
      "2018年报": 358.302592
    }
  },
  {
    "segment": "油气销售",
    "periods": {
      "2025半年报": 1717.45,
      "2024年报": 3556.15,
      "2024半年报": 1851.12,
      "2023年报": 3278.67,
      "2023半年报": 1516.86,
      "2022年报": 3529.56,
      "2022半年报": 1766.81,
      "2021年报": 2221.25,
      "2021半年报": 1006.251361,
      "2020年报": 1396.01,
      "2019年报": 1971.725904,
      "2018年报": 1865.565568
    }
  }
]